pylocatorconvt/__init__.py
pylocatorconvt/locator_package.py
pylocatorconvt/locatorconvt.py
pylocatorconvt-1.0.1.dist-info/LICENSE
pylocatorconvt-1.0.1.dist-info/METADATA
pylocatorconvt-1.0.1.dist-info/WHEEL
pylocatorconvt-1.0.1.dist-info/top_level.txt
pylocatorconvt-1.0.1.dist-info/RECORD
